limited_time_token_handler/__init__.py
limited_time_token_handler/limited_time_token_decoder.py
limited_time_token_handler/limited_time_token_generator.py
limited_time_token_handler/token_error.py
limited_time_token_handler-0.1.9.dist-info/LICENSE
limited_time_token_handler-0.1.9.dist-info/METADATA
limited_time_token_handler-0.1.9.dist-info/WHEEL
limited_time_token_handler-0.1.9.dist-info/top_level.txt
limited_time_token_handler-0.1.9.dist-info/RECORD
