Metadata-Version: 2.1
Name: limited-time-token-handler
Version: 0.1.9
Summary: A Python package designed to handle secure, time-limited token generation and validation.
Home-page: https://github.com/shaileshpandit141/limited-time-token-handler.git
Author: shailesh
Author-email: shaileshpandit141@gmail.com
Classifier: Programming Language :: Python :: 3
Classifier: License :: OSI Approved :: MIT License
Classifier: Operating System :: OS Independent
Requires-Python: >=3.7
License-File: LICENSE
Requires-Dist: itsdangerous>=2.1.2
Requires-Dist: python-decouple>=3.6
